tfbuild/actions.py
tfbuild/cli.py
tfbuild/core.py
tfbuild/workspace.py
tfbuild-1.4.1.dist-info/LICENSE
tfbuild-1.4.1.dist-info/METADATA
tfbuild-1.4.1.dist-info/WHEEL
tfbuild-1.4.1.dist-info/entry_points.txt
tfbuild-1.4.1.dist-info/top_level.txt
tfbuild-1.4.1.dist-info/RECORD
