Metadata-Version: 2.2
Name: tfbuild
Version: 1.4.1
Summary: TFBuild is a command line tool for Terraform 
Home-page: https://github.com/mpearson117/tfbuild
Author: Michael Pearson
Classifier: Development Status :: 5 - Production/Stable
Classifier: Environment :: Console
Classifier: Intended Audience :: Information Technology
Classifier: Intended Audience :: System Administrators
Classifier: License :: OSI Approved :: Apache Software License
Classifier: Natural Language :: English
Classifier: Programming Language :: Python
Classifier: Topic :: Software Development :: Libraries
Classifier: Topic :: Software Development :: Pre-processors
Classifier: Topic :: System :: Systems Administration
License-File: LICENSE
Requires-Dist: boto3
Requires-Dist: colorlog
Requires-Dist: confuse
Requires-Dist: GitPython
Requires-Dist: jsonpickle
Requires-Dist: py_console
Requires-Dist: PyYAML
Requires-Dist: pyhcl
Requires-Dist: requests
Provides-Extra: dev
Requires-Dist: pytest<6,>=5.0; python_version > "3" and extra == "dev"
Requires-Dist: pytest-cov; extra == "dev"
Requires-Dist: codecov; extra == "dev"
Requires-Dist: pytest-mock; extra == "dev"
Dynamic: author
Dynamic: classifier
Dynamic: description
Dynamic: description-content-type
Dynamic: home-page
Dynamic: provides-extra
Dynamic: requires-dist
Dynamic: summary
